[
  {
    "block": "semi_real_main",
    "task_family": "semi_real_field",
    "task": "amount",
    "setting": "labeled25_unlabeled100",
    "variant": "B0_unconstrained",
    "variant_family": "B0",
    "runs": "2",
    "mean_p_event": "0.7831624214847883",
    "delta_p_event": "0.0",
    "ci95_delta_p_event": "0.0",
    "up_rate_p_event": "",
    "mean_illegal_mass": "0.21683757851521174",
    "delta_illegal_mass": "0.0",
    "low_p_event_rate": "0.013333333333333334",
    "unconstrained_event_rate": "0.9216666666666666",
    "delta_unconstrained_event_rate": "0.0",
    "up_rate_legal": "",
    "constrained_event_rate": "1.0",
    "char_accuracy": "0.8127777777777778",
    "delta_char_accuracy": "0.0",
    "up_rate_char": "",
    "constrained_char_accuracy": "0.8138888888888889",
    "delta_constrained_char_accuracy": "0.0",
    "exact_sequence_accuracy": "0.20666666666666667",
    "delta_exact_sequence_accuracy": "0.0",
    "up_rate_exact": "",
    "constrained_exact_sequence_accuracy": "0.21000000000000002",
    "delta_constrained_exact_sequence_accuracy": "0.0",
    "mean_nll": "0.6235815854867299",
    "hidden_conflict_rate": "0.013333333333333334",
    "fairness_flags": "warn_b1_b3_not_independent_rows",
    "claim_use": "partial semi-real evidence",
    "notes": ""
  },
  {
    "block": "semi_real_main",
    "task_family": "semi_real_field",
    "task": "amount",
    "setting": "labeled25_unlabeled100",
    "variant": "B2_event_0.1",
    "variant_family": "B2",
    "runs": "2",
    "mean_p_event": "0.7745091248055299",
    "delta_p_event": "-0.008653296679258349",
    "ci95_delta_p_event": "0.0009485852817694274",
    "up_rate_p_event": "",
    "mean_illegal_mass": "0.2254908751944701",
    "delta_illegal_mass": "0.008653296679258349",
    "low_p_event_rate": "0.016666666666666666",
    "unconstrained_event_rate": "0.905",
    "delta_unconstrained_event_rate": "-0.016666666666666663",
    "up_rate_legal": "",
    "constrained_event_rate": "1.0",
    "char_accuracy": "0.8119444444444445",
    "delta_char_accuracy": "-0.0008333333333332971",
    "up_rate_char": "",
    "constrained_char_accuracy": "0.8133333333333332",
    "delta_constrained_char_accuracy": "-0.0005555555555555869",
    "exact_sequence_accuracy": "0.20500000000000002",
    "delta_exact_sequence_accuracy": "-0.0016666666666666635",
    "up_rate_exact": "",
    "constrained_exact_sequence_accuracy": "0.21000000000000002",
    "delta_constrained_exact_sequence_accuracy": "0.0",
    "mean_nll": "0.6362371632787915",
    "hidden_conflict_rate": "0.016666666666666666",
    "fairness_flags": "warn_b1_b3_not_independent_rows",
    "claim_use": "partial semi-real evidence",
    "notes": ""
  },
  {
    "block": "semi_real_main",
    "task_family": "semi_real_field",
    "task": "amount",
    "setting": "labeled25_unlabeled100",
    "variant": "B2_event_0.5",
    "variant_family": "B2",
    "runs": "2",
    "mean_p_event": "0.7388452879091103",
    "delta_p_event": "-0.0443171335756779",
    "ci95_delta_p_event": "0.018272038239240524",
    "up_rate_p_event": "",
    "mean_illegal_mass": "0.26115471209088964",
    "delta_illegal_mass": "0.0443171335756779",
    "low_p_event_rate": "0.07666666666666666",
    "unconstrained_event_rate": "0.7733333333333334",
    "delta_unconstrained_event_rate": "-0.14833333333333332",
    "up_rate_legal": "",
    "constrained_event_rate": "1.0",
    "char_accuracy": "0.8",
    "delta_char_accuracy": "-0.012777777777777777",
    "up_rate_char": "",
    "constrained_char_accuracy": "0.8019444444444445",
    "delta_constrained_char_accuracy": "-0.011944444444444424",
    "exact_sequence_accuracy": "0.17333333333333334",
    "delta_exact_sequence_accuracy": "-0.033333333333333326",
    "up_rate_exact": "",
    "constrained_exact_sequence_accuracy": "0.17666666666666667",
    "delta_constrained_exact_sequence_accuracy": "-0.03333333333333334",
    "mean_nll": "0.6694939022594029",
    "hidden_conflict_rate": "0.07666666666666666",
    "fairness_flags": "warn_b1_b3_not_independent_rows",
    "claim_use": "partial semi-real evidence",
    "notes": ""
  },
  {
    "block": "semi_real_main",
    "task_family": "semi_real_field",
    "task": "amount",
    "setting": "labeled25_unlabeled100",
    "variant": "B4_semi_event_0.1",
    "variant_family": "B4",
    "runs": "2",
    "mean_p_event": "0.9302845085660616",
    "delta_p_event": "0.1471220870812734",
    "ci95_delta_p_event": "0.025533302466074815",
    "up_rate_p_event": "",
    "mean_illegal_mass": "0.06971549143393835",
    "delta_illegal_mass": "-0.1471220870812734",
    "low_p_event_rate": "0.0",
    "unconstrained_event_rate": "1.0",
    "delta_unconstrained_event_rate": "0.07833333333333331",
    "up_rate_legal": "",
    "constrained_event_rate": "1.0",
    "char_accuracy": "0.8366666666666667",
    "delta_char_accuracy": "0.023888888888888904",
    "up_rate_char": "",
    "constrained_char_accuracy": "0.8366666666666667",
    "delta_constrained_char_accuracy": "0.022777777777777786",
    "exact_sequence_accuracy": "0.27",
    "delta_exact_sequence_accuracy": "0.06333333333333332",
    "up_rate_exact": "",
    "constrained_exact_sequence_accuracy": "0.27",
    "delta_constrained_exact_sequence_accuracy": "0.059999999999999984",
    "mean_nll": "0.5674525104628669",
    "hidden_conflict_rate": "0.0",
    "fairness_flags": "warn_b1_b3_not_independent_rows",
    "claim_use": "partial semi-real evidence",
    "notes": ""
  },
  {
    "block": "semi_real_main",
    "task_family": "semi_real_field",
    "task": "amount",
    "setting": "labeled25_unlabeled100",
    "variant": "B4_semi_event_0.5",
    "variant_family": "B4",
    "runs": "2",
    "mean_p_event": "0.9660899843772253",
    "delta_p_event": "0.182927562892437",
    "ci95_delta_p_event": "0.027298630448182468",
    "up_rate_p_event": "",
    "mean_illegal_mass": "0.033910015622774736",
    "delta_illegal_mass": "-0.182927562892437",
    "low_p_event_rate": "0.0",
    "unconstrained_event_rate": "1.0",
    "delta_unconstrained_event_rate": "0.07833333333333331",
    "up_rate_legal": "",
    "constrained_event_rate": "1.0",
    "char_accuracy": "0.826111111111111",
    "delta_char_accuracy": "0.013333333333333308",
    "up_rate_char": "",
    "constrained_char_accuracy": "0.826111111111111",
    "delta_constrained_char_accuracy": "0.01222222222222219",
    "exact_sequence_accuracy": "0.27",
    "delta_exact_sequence_accuracy": "0.06333333333333335",
    "up_rate_exact": "",
    "constrained_exact_sequence_accuracy": "0.27",
    "delta_constrained_exact_sequence_accuracy": "0.06000000000000001",
    "mean_nll": "0.6178235097726186",
    "hidden_conflict_rate": "0.0",
    "fairness_flags": "warn_b1_b3_not_independent_rows",
    "claim_use": "partial semi-real evidence",
    "notes": ""
  },
  {
    "block": "semi_real_main",
    "task_family": "semi_real_field",
    "task": "amount",
    "setting": "labeled25_unlabeled100",
    "variant": "B5_rule_feature_0.8",
    "variant_family": "B5",
    "runs": "2",
    "mean_p_event": "0.8641710997621218",
    "delta_p_event": "0.08100867827733355",
    "ci95_delta_p_event": "0.010474894730250171",
    "up_rate_p_event": "",
    "mean_illegal_mass": "0.1358289002378782",
    "delta_illegal_mass": "-0.08100867827733355",
    "low_p_event_rate": "0.0",
    "unconstrained_event_rate": "0.9933333333333333",
    "delta_unconstrained_event_rate": "0.0716666666666666",
    "up_rate_legal": "",
    "constrained_event_rate": "1.0",
    "char_accuracy": "0.8297222222222222",
    "delta_char_accuracy": "0.01694444444444443",
    "up_rate_char": "",
    "constrained_char_accuracy": "0.8302777777777777",
    "delta_constrained_char_accuracy": "0.016388888888888842",
    "exact_sequence_accuracy": "0.2516666666666667",
    "delta_exact_sequence_accuracy": "0.04500000000000001",
    "up_rate_exact": "",
    "constrained_exact_sequence_accuracy": "0.2516666666666667",
    "delta_constrained_exact_sequence_accuracy": "0.04166666666666667",
    "mean_nll": "0.5659987468189663",
    "hidden_conflict_rate": "0.0",
    "fairness_flags": "warn_b1_b3_not_independent_rows;warn_local_style_baseline",
    "claim_use": "partial semi-real evidence",
    "notes": ""
  },
  {
    "block": "semi_real_main",
    "task_family": "semi_real_field",
    "task": "amount",
    "setting": "labeled25_unlabeled100",
    "variant": "B6_pr_style_tau0.8",
    "variant_family": "B6",
    "runs": "2",
    "mean_p_event": "0.8809641182422638",
    "delta_p_event": "0.09780169675747558",
    "ci95_delta_p_event": "0.01546628681421288",
    "up_rate_p_event": "",
    "mean_illegal_mass": "0.11903588175773616",
    "delta_illegal_mass": "-0.09780169675747558",
    "low_p_event_rate": "0.0",
    "unconstrained_event_rate": "0.9966666666666666",
    "delta_unconstrained_event_rate": "0.07499999999999996",
    "up_rate_legal": "",
    "constrained_event_rate": "1.0",
    "char_accuracy": "0.8369444444444445",
    "delta_char_accuracy": "0.02416666666666667",
    "up_rate_char": "",
    "constrained_char_accuracy": "0.8372222222222223",
    "delta_constrained_char_accuracy": "0.023333333333333373",
    "exact_sequence_accuracy": "0.2683333333333333",
    "delta_exact_sequence_accuracy": "0.06166666666666665",
    "up_rate_exact": "",
    "constrained_exact_sequence_accuracy": "0.2683333333333333",
    "delta_constrained_exact_sequence_accuracy": "0.058333333333333307",
    "mean_nll": "0.540530216826333",
    "hidden_conflict_rate": "0.0",
    "fairness_flags": "warn_b1_b3_not_independent_rows;warn_local_style_baseline",
    "claim_use": "partial semi-real evidence",
    "notes": ""
  },
  {
    "block": "semi_real_main",
    "task_family": "semi_real_field",
    "task": "product_code",
    "setting": "labeled25_unlabeled100",
    "variant": "B0_unconstrained",
    "variant_family": "B0",
    "runs": "2",
    "mean_p_event": "0.7658134392648935",
    "delta_p_event": "0.0",
    "ci95_delta_p_event": "0.0",
    "up_rate_p_event": "",
    "mean_illegal_mass": "0.23418656073510646",
    "delta_illegal_mass": "0.0",
    "low_p_event_rate": "0.041666666666666664",
    "unconstrained_event_rate": "0.9566666666666667",
    "delta_unconstrained_event_rate": "0.0",
    "up_rate_legal": "",
    "constrained_event_rate": "1.0",
    "char_accuracy": "0.7194444444444444",
    "delta_char_accuracy": "0.0",
    "up_rate_char": "",
    "constrained_char_accuracy": "0.7238888888888889",
    "delta_constrained_char_accuracy": "0.0",
    "exact_sequence_accuracy": "0.06333333333333334",
    "delta_exact_sequence_accuracy": "0.0",
    "up_rate_exact": "",
    "constrained_exact_sequence_accuracy": "0.06333333333333334",
    "delta_constrained_exact_sequence_accuracy": "0.0",
    "mean_nll": "0.9594049298101002",
    "hidden_conflict_rate": "0.041666666666666664",
    "fairness_flags": "warn_b1_b3_not_independent_rows",
    "claim_use": "partial semi-real evidence",
    "notes": ""
  },
  {
    "block": "semi_real_main",
    "task_family": "semi_real_field",
    "task": "product_code",
    "setting": "labeled25_unlabeled100",
    "variant": "B2_event_0.1",
    "variant_family": "B2",
    "runs": "2",
    "mean_p_event": "0.7637338800231616",
    "delta_p_event": "-0.0020795592417319764",
    "ci95_delta_p_event": "0.002150552190343457",
    "up_rate_p_event": "",
    "mean_illegal_mass": "0.23626611997683844",
    "delta_illegal_mass": "0.0020795592417319764",
    "low_p_event_rate": "0.04",
    "unconstrained_event_rate": "0.9550000000000001",
    "delta_unconstrained_event_rate": "-0.0016666666666666496",
    "up_rate_legal": "",
    "constrained_event_rate": "1.0",
    "char_accuracy": "0.7194444444444444",
    "delta_char_accuracy": "0.0",
    "up_rate_char": "",
    "constrained_char_accuracy": "0.7233333333333334",
    "delta_constrained_char_accuracy": "-0.0005555555555555869",
    "exact_sequence_accuracy": "0.06333333333333334",
    "delta_exact_sequence_accuracy": "0.0",
    "up_rate_exact": "",
    "constrained_exact_sequence_accuracy": "0.06333333333333334",
    "delta_constrained_exact_sequence_accuracy": "0.0",
    "mean_nll": "0.9778258517053393",
    "hidden_conflict_rate": "0.04",
    "fairness_flags": "warn_b1_b3_not_independent_rows",
    "claim_use": "partial semi-real evidence",
    "notes": ""
  },
  {
    "block": "semi_real_main",
    "task_family": "semi_real_field",
    "task": "product_code",
    "setting": "labeled25_unlabeled100",
    "variant": "B2_event_0.5",
    "variant_family": "B2",
    "runs": "2",
    "mean_p_event": "0.7586942677199842",
    "delta_p_event": "-0.007119171544909431",
    "ci95_delta_p_event": "0.005184288000067038",
    "up_rate_p_event": "",
    "mean_illegal_mass": "0.2413057322800159",
    "delta_illegal_mass": "0.007119171544909431",
    "low_p_event_rate": "0.04166666666666667",
    "unconstrained_event_rate": "0.9483333333333334",
    "delta_unconstrained_event_rate": "-0.008333333333333304",
    "up_rate_legal": "",
    "constrained_event_rate": "1.0",
    "char_accuracy": "0.7119444444444445",
    "delta_char_accuracy": "-0.007500000000000007",
    "up_rate_char": "",
    "constrained_char_accuracy": "0.7144444444444444",
    "delta_constrained_char_accuracy": "-0.009444444444444478",
    "exact_sequence_accuracy": "0.04666666666666666",
    "delta_exact_sequence_accuracy": "-0.016666666666666673",
    "up_rate_exact": "",
    "constrained_exact_sequence_accuracy": "0.04666666666666666",
    "delta_constrained_exact_sequence_accuracy": "-0.016666666666666673",
    "mean_nll": "1.0994136243396335",
    "hidden_conflict_rate": "0.04166666666666667",
    "fairness_flags": "warn_b1_b3_not_independent_rows",
    "claim_use": "partial semi-real evidence",
    "notes": ""
  },
  {
    "block": "semi_real_main",
    "task_family": "semi_real_field",
    "task": "product_code",
    "setting": "labeled25_unlabeled100",
    "variant": "B4_semi_event_0.1",
    "variant_family": "B4",
    "runs": "2",
    "mean_p_event": "0.9346086685856183",
    "delta_p_event": "0.16879522932072477",
    "ci95_delta_p_event": "0.015004266163706708",
    "up_rate_p_event": "",
    "mean_illegal_mass": "0.06539133141438169",
    "delta_illegal_mass": "-0.16879522932072477",
    "low_p_event_rate": "0.0",
    "unconstrained_event_rate": "1.0",
    "delta_unconstrained_event_rate": "0.043333333333333335",
    "up_rate_legal": "",
    "constrained_event_rate": "1.0",
    "char_accuracy": "0.7483333333333333",
    "delta_char_accuracy": "0.02888888888888891",
    "up_rate_char": "",
    "constrained_char_accuracy": "0.7483333333333333",
    "delta_constrained_char_accuracy": "0.024444444444444435",
    "exact_sequence_accuracy": "0.11666666666666667",
    "delta_exact_sequence_accuracy": "0.05333333333333334",
    "up_rate_exact": "",
    "constrained_exact_sequence_accuracy": "0.11666666666666667",
    "delta_constrained_exact_sequence_accuracy": "0.05333333333333334",
    "mean_nll": "0.9390616004334555",
    "hidden_conflict_rate": "0.0",
    "fairness_flags": "warn_b1_b3_not_independent_rows",
    "claim_use": "partial semi-real evidence",
    "notes": ""
  },
  {
    "block": "semi_real_main",
    "task_family": "semi_real_field",
    "task": "product_code",
    "setting": "labeled25_unlabeled100",
    "variant": "B4_semi_event_0.5",
    "variant_family": "B4",
    "runs": "2",
    "mean_p_event": "0.9742269866665205",
    "delta_p_event": "0.20841354740162693",
    "ci95_delta_p_event": "0.01949549162089826",
    "up_rate_p_event": "",
    "mean_illegal_mass": "0.025773013333479533",
    "delta_illegal_mass": "-0.20841354740162693",
    "low_p_event_rate": "0.0",
    "unconstrained_event_rate": "1.0",
    "delta_unconstrained_event_rate": "0.043333333333333335",
    "up_rate_legal": "",
    "constrained_event_rate": "1.0",
    "char_accuracy": "0.7413888888888889",
    "delta_char_accuracy": "0.021944444444444433",
    "up_rate_char": "",
    "constrained_char_accuracy": "0.7413888888888889",
    "delta_constrained_char_accuracy": "0.01749999999999996",
    "exact_sequence_accuracy": "0.09833333333333333",
    "delta_exact_sequence_accuracy": "0.034999999999999996",
    "up_rate_exact": "",
    "constrained_exact_sequence_accuracy": "0.09833333333333333",
    "delta_constrained_exact_sequence_accuracy": "0.034999999999999996",
    "mean_nll": "0.9874749918778738",
    "hidden_conflict_rate": "0.0",
    "fairness_flags": "warn_b1_b3_not_independent_rows",
    "claim_use": "partial semi-real evidence",
    "notes": ""
  },
  {
    "block": "semi_real_main",
    "task_family": "semi_real_field",
    "task": "product_code",
    "setting": "labeled25_unlabeled100",
    "variant": "B5_rule_feature_0.8",
    "variant_family": "B5",
    "runs": "2",
    "mean_p_event": "0.8570589944223563",
    "delta_p_event": "0.09124555515746274",
    "ci95_delta_p_event": "0.007409886446595249",
    "up_rate_p_event": "",
    "mean_illegal_mass": "0.14294100557764372",
    "delta_illegal_mass": "-0.09124555515746274",
    "low_p_event_rate": "0.0033333333333333335",
    "unconstrained_event_rate": "0.9866666666666666",
    "delta_unconstrained_event_rate": "0.02999999999999997",
    "up_rate_legal": "",
    "constrained_event_rate": "1.0",
    "char_accuracy": "0.7252777777777778",
    "delta_char_accuracy": "0.005833333333333357",
    "up_rate_char": "",
    "constrained_char_accuracy": "0.7261111111111112",
    "delta_constrained_char_accuracy": "0.002222222222222181",
    "exact_sequence_accuracy": "0.065",
    "delta_exact_sequence_accuracy": "0.0016666666666666635",
    "up_rate_exact": "",
    "constrained_exact_sequence_accuracy": "0.065",
    "delta_constrained_exact_sequence_accuracy": "0.0016666666666666635",
    "mean_nll": "0.9126945671770308",
    "hidden_conflict_rate": "0.0033333333333333335",
    "fairness_flags": "warn_b1_b3_not_independent_rows;warn_local_style_baseline",
    "claim_use": "partial semi-real evidence",
    "notes": ""
  },
  {
    "block": "semi_real_main",
    "task_family": "semi_real_field",
    "task": "product_code",
    "setting": "labeled25_unlabeled100",
    "variant": "B6_pr_style_tau0.8",
    "variant_family": "B6",
    "runs": "2",
    "mean_p_event": "0.8794230534633001",
    "delta_p_event": "0.11360961419840654",
    "ci95_delta_p_event": "0.020448286597927308",
    "up_rate_p_event": "",
    "mean_illegal_mass": "0.12057694653669992",
    "delta_illegal_mass": "-0.11360961419840654",
    "low_p_event_rate": "0.0",
    "unconstrained_event_rate": "0.99",
    "delta_unconstrained_event_rate": "0.033333333333333326",
    "up_rate_legal": "",
    "constrained_event_rate": "1.0",
    "char_accuracy": "0.7519444444444445",
    "delta_char_accuracy": "0.03250000000000003",
    "up_rate_char": "",
    "constrained_char_accuracy": "0.7533333333333333",
    "delta_constrained_char_accuracy": "0.029444444444444384",
    "exact_sequence_accuracy": "0.11666666666666667",
    "delta_exact_sequence_accuracy": "0.05333333333333334",
    "up_rate_exact": "",
    "constrained_exact_sequence_accuracy": "0.11666666666666667",
    "delta_constrained_exact_sequence_accuracy": "0.05333333333333334",
    "mean_nll": "0.8846303143103917",
    "hidden_conflict_rate": "0.0",
    "fairness_flags": "warn_b1_b3_not_independent_rows;warn_local_style_baseline",
    "claim_use": "partial semi-real evidence",
    "notes": ""
  },
  {
    "block": "learning_curve",
    "task_family": "semi_real_field",
    "task": "amount",
    "setting": "labeled10_unlabeled100",
    "variant": "B0_unconstrained",
    "variant_family": "B0",
    "runs": "2",
    "mean_p_event": "0.6097660051584244",
    "delta_p_event": "0.0",
    "ci95_delta_p_event": "0.0",
    "up_rate_p_event": "",
    "mean_illegal_mass": "0.3902339948415756",
    "delta_illegal_mass": "0.0",
    "low_p_event_rate": "0.20400000000000001",
    "unconstrained_event_rate": "0.838",
    "delta_unconstrained_event_rate": "0.0",
    "up_rate_legal": "",
    "constrained_event_rate": "1.0",
    "char_accuracy": "0.675",
    "delta_char_accuracy": "0.0",
    "up_rate_char": "",
    "constrained_char_accuracy": "0.6796666666666666",
    "delta_constrained_char_accuracy": "0.0",
    "exact_sequence_accuracy": "0.03",
    "delta_exact_sequence_accuracy": "0.0",
    "up_rate_exact": "",
    "constrained_exact_sequence_accuracy": "0.034",
    "delta_constrained_exact_sequence_accuracy": "0.0",
    "mean_nll": "1.3455052038828532",
    "hidden_conflict_rate": "0.20400000000000001",
    "fairness_flags": "warn_b1_b3_not_independent_rows;warn_partial_baseline_grid",
    "claim_use": "partial semi-real evidence",
    "notes": ""
  },
  {
    "block": "learning_curve",
    "task_family": "semi_real_field",
    "task": "amount",
    "setting": "labeled10_unlabeled100",
    "variant": "B4_semi_event_0.1",
    "variant_family": "B4",
    "runs": "2",
    "mean_p_event": "0.9386905570030213",
    "delta_p_event": "0.3289245518445969",
    "ci95_delta_p_event": "0.03167547287464143",
    "up_rate_p_event": "",
    "mean_illegal_mass": "0.061309442996978714",
    "delta_illegal_mass": "-0.3289245518445969",
    "low_p_event_rate": "0.0",
    "unconstrained_event_rate": "0.996",
    "delta_unconstrained_event_rate": "0.15800000000000003",
    "up_rate_legal": "",
    "constrained_event_rate": "1.0",
    "char_accuracy": "0.6696666666666666",
    "delta_char_accuracy": "-0.005333333333333357",
    "up_rate_char": "",
    "constrained_char_accuracy": "0.6696666666666666",
    "delta_constrained_char_accuracy": "-0.010000000000000009",
    "exact_sequence_accuracy": "0.034",
    "delta_exact_sequence_accuracy": "0.003999999999999998",
    "up_rate_exact": "",
    "constrained_exact_sequence_accuracy": "0.034",
    "delta_constrained_exact_sequence_accuracy": "0.0",
    "mean_nll": "1.4367087025642395",
    "hidden_conflict_rate": "0.0",
    "fairness_flags": "warn_b1_b3_not_independent_rows;warn_partial_baseline_grid",
    "claim_use": "partial semi-real evidence",
    "notes": ""
  },
  {
    "block": "learning_curve",
    "task_family": "semi_real_field",
    "task": "amount",
    "setting": "labeled25_unlabeled100",
    "variant": "B0_unconstrained",
    "variant_family": "B0",
    "runs": "2",
    "mean_p_event": "0.7834720315933228",
    "delta_p_event": "0.0",
    "ci95_delta_p_event": "0.0",
    "up_rate_p_event": "",
    "mean_illegal_mass": "0.21652796840667726",
    "delta_illegal_mass": "0.0",
    "low_p_event_rate": "0.016",
    "unconstrained_event_rate": "0.918",
    "delta_unconstrained_event_rate": "0.0",
    "up_rate_legal": "",
    "constrained_event_rate": "1.0",
    "char_accuracy": "0.8076666666666668",
    "delta_char_accuracy": "0.0",
    "up_rate_char": "",
    "constrained_char_accuracy": "0.8083333333333333",
    "delta_constrained_char_accuracy": "0.0",
    "exact_sequence_accuracy": "0.192",
    "delta_exact_sequence_accuracy": "0.0",
    "up_rate_exact": "",
    "constrained_exact_sequence_accuracy": "0.192",
    "delta_constrained_exact_sequence_accuracy": "0.0",
    "mean_nll": "0.6287848156293234",
    "hidden_conflict_rate": "0.016",
    "fairness_flags": "warn_b1_b3_not_independent_rows;warn_partial_baseline_grid",
    "claim_use": "partial semi-real evidence",
    "notes": ""
  },
  {
    "block": "learning_curve",
    "task_family": "semi_real_field",
    "task": "amount",
    "setting": "labeled25_unlabeled100",
    "variant": "B4_semi_event_0.1",
    "variant_family": "B4",
    "runs": "2",
    "mean_p_event": "0.9297657436132432",
    "delta_p_event": "0.14629371201992036",
    "ci95_delta_p_event": "0.026588551774024936",
    "up_rate_p_event": "",
    "mean_illegal_mass": "0.0702342563867569",
    "delta_illegal_mass": "-0.14629371201992036",
    "low_p_event_rate": "0.0",
    "unconstrained_event_rate": "1.0",
    "delta_unconstrained_event_rate": "0.08199999999999996",
    "up_rate_legal": "",
    "constrained_event_rate": "1.0",
    "char_accuracy": "0.8313333333333333",
    "delta_char_accuracy": "0.023666666666666614",
    "up_rate_char": "",
    "constrained_char_accuracy": "0.8313333333333333",
    "delta_constrained_char_accuracy": "0.022999999999999965",
    "exact_sequence_accuracy": "0.252",
    "delta_exact_sequence_accuracy": "0.06000000000000001",
    "up_rate_exact": "",
    "constrained_exact_sequence_accuracy": "0.252",
    "delta_constrained_exact_sequence_accuracy": "0.06000000000000001",
    "mean_nll": "0.5740329697926839",
    "hidden_conflict_rate": "0.0",
    "fairness_flags": "warn_b1_b3_not_independent_rows;warn_partial_baseline_grid",
    "claim_use": "partial semi-real evidence",
    "notes": ""
  },
  {
    "block": "learning_curve",
    "task_family": "semi_real_field",
    "task": "amount",
    "setting": "labeled50_unlabeled100",
    "variant": "B0_unconstrained",
    "variant_family": "B0",
    "runs": "2",
    "mean_p_event": "0.8945429023504258",
    "delta_p_event": "0.0",
    "ci95_delta_p_event": "0.0",
    "up_rate_p_event": "",
    "mean_illegal_mass": "0.10545709764957423",
    "delta_illegal_mass": "0.0",
    "low_p_event_rate": "0.0",
    "unconstrained_event_rate": "0.964",
    "delta_unconstrained_event_rate": "0.0",
    "up_rate_legal": "",
    "constrained_event_rate": "1.0",
    "char_accuracy": "0.9486666666666667",
    "delta_char_accuracy": "0.0",
    "up_rate_char": "",
    "constrained_char_accuracy": "0.9516666666666667",
    "delta_constrained_char_accuracy": "0.0",
    "exact_sequence_accuracy": "0.72",
    "delta_exact_sequence_accuracy": "0.0",
    "up_rate_exact": "",
    "constrained_exact_sequence_accuracy": "0.734",
    "delta_constrained_exact_sequence_accuracy": "0.0",
    "mean_nll": "0.24345192432403565",
    "hidden_conflict_rate": "0.0",
    "fairness_flags": "warn_b1_b3_not_independent_rows;warn_partial_baseline_grid",
    "claim_use": "partial semi-real evidence",
    "notes": ""
  },
  {
    "block": "learning_curve",
    "task_family": "semi_real_field",
    "task": "amount",
    "setting": "labeled50_unlabeled100",
    "variant": "B4_semi_event_0.1",
    "variant_family": "B4",
    "runs": "2",
    "mean_p_event": "0.9544371197223663",
    "delta_p_event": "0.05989421737194056",
    "ci95_delta_p_event": "0.02012977404117587",
    "up_rate_p_event": "",
    "mean_illegal_mass": "0.045562880277633666",
    "delta_illegal_mass": "-0.05989421737194056",
    "low_p_event_rate": "0.0",
    "unconstrained_event_rate": "0.998",
    "delta_unconstrained_event_rate": "0.03400000000000003",
    "up_rate_legal": "",
    "constrained_event_rate": "1.0",
    "char_accuracy": "0.957",
    "delta_char_accuracy": "0.008333333333333304",
    "up_rate_char": "",
    "constrained_char_accuracy": "0.9573333333333334",
    "delta_constrained_char_accuracy": "0.005666666666666653",
    "exact_sequence_accuracy": "0.754",
    "delta_exact_sequence_accuracy": "0.033999999999999975",
    "up_rate_exact": "",
    "constrained_exact_sequence_accuracy": "0.756",
    "delta_constrained_exact_sequence_accuracy": "0.021999999999999964",
    "mean_nll": "0.19050674152374267",
    "hidden_conflict_rate": "0.0",
    "fairness_flags": "warn_b1_b3_not_independent_rows;warn_partial_baseline_grid",
    "claim_use": "partial semi-real evidence",
    "notes": ""
  },
  {
    "block": "learning_curve",
    "task_family": "semi_real_field",
    "task": "amount",
    "setting": "labeled5_unlabeled100",
    "variant": "B0_unconstrained",
    "variant_family": "B0",
    "runs": "2",
    "mean_p_event": "0.2849607473909855",
    "delta_p_event": "0.0",
    "ci95_delta_p_event": "0.0",
    "up_rate_p_event": "",
    "mean_illegal_mass": "0.7150392526090145",
    "delta_illegal_mass": "0.0",
    "low_p_event_rate": "0.988",
    "unconstrained_event_rate": "0.852",
    "delta_unconstrained_event_rate": "0.0",
    "up_rate_legal": "",
    "constrained_event_rate": "1.0",
    "char_accuracy": "0.576",
    "delta_char_accuracy": "0.0",
    "up_rate_char": "",
    "constrained_char_accuracy": "0.577",
    "delta_constrained_char_accuracy": "0.0",
    "exact_sequence_accuracy": "0.002",
    "delta_exact_sequence_accuracy": "0.0",
    "up_rate_exact": "",
    "constrained_exact_sequence_accuracy": "0.002",
    "delta_constrained_exact_sequence_accuracy": "0.0",
    "mean_nll": "1.7864861097335816",
    "hidden_conflict_rate": "0.988",
    "fairness_flags": "warn_b1_b3_not_independent_rows;warn_partial_baseline_grid",
    "claim_use": "partial semi-real evidence",
    "notes": ""
  },
  {
    "block": "learning_curve",
    "task_family": "semi_real_field",
    "task": "amount",
    "setting": "labeled5_unlabeled100",
    "variant": "B4_semi_event_0.1",
    "variant_family": "B4",
    "runs": "2",
    "mean_p_event": "0.9560034395456314",
    "delta_p_event": "0.671042692154646",
    "ci95_delta_p_event": "0.031229030238389962",
    "up_rate_p_event": "",
    "mean_illegal_mass": "0.043996560454368616",
    "delta_illegal_mass": "-0.6710426921546458",
    "low_p_event_rate": "0.0",
    "unconstrained_event_rate": "0.998",
    "delta_unconstrained_event_rate": "0.14600000000000002",
    "up_rate_legal": "",
    "constrained_event_rate": "1.0",
    "char_accuracy": "0.5723333333333334",
    "delta_char_accuracy": "-0.003666666666666596",
    "up_rate_char": "",
    "constrained_char_accuracy": "0.5720000000000001",
    "delta_constrained_char_accuracy": "-0.0050000000000000044",
    "exact_sequence_accuracy": "0.01",
    "delta_exact_sequence_accuracy": "0.008",
    "up_rate_exact": "",
    "constrained_exact_sequence_accuracy": "0.01",
    "delta_constrained_exact_sequence_accuracy": "0.008",
    "mean_nll": "2.0339084361394244",
    "hidden_conflict_rate": "0.0",
    "fairness_flags": "warn_b1_b3_not_independent_rows;warn_partial_baseline_grid",
    "claim_use": "partial semi-real evidence",
    "notes": ""
  },
  {
    "block": "learning_curve",
    "task_family": "semi_real_field",
    "task": "product_code",
    "setting": "labeled10_unlabeled100",
    "variant": "B0_unconstrained",
    "variant_family": "B0",
    "runs": "2",
    "mean_p_event": "0.5974949382543564",
    "delta_p_event": "0.0",
    "ci95_delta_p_event": "0.0",
    "up_rate_p_event": "",
    "mean_illegal_mass": "0.4025050617456436",
    "delta_illegal_mass": "0.0",
    "low_p_event_rate": "0.222",
    "unconstrained_event_rate": "0.97",
    "delta_unconstrained_event_rate": "0.0",
    "up_rate_legal": "",
    "constrained_event_rate": "1.0",
    "char_accuracy": "0.5343333333333333",
    "delta_char_accuracy": "0.0",
    "up_rate_char": "",
    "constrained_char_accuracy": "0.5363333333333333",
    "delta_constrained_char_accuracy": "0.0",
    "exact_sequence_accuracy": "0.002",
    "delta_exact_sequence_accuracy": "0.0",
    "up_rate_exact": "",
    "constrained_exact_sequence_accuracy": "0.002",
    "delta_constrained_exact_sequence_accuracy": "0.0",
    "mean_nll": "2.012773956298828",
    "hidden_conflict_rate": "0.222",
    "fairness_flags": "warn_b1_b3_not_independent_rows;warn_partial_baseline_grid",
    "claim_use": "partial semi-real evidence",
    "notes": ""
  },
  {
    "block": "learning_curve",
    "task_family": "semi_real_field",
    "task": "product_code",
    "setting": "labeled10_unlabeled100",
    "variant": "B4_semi_event_0.1",
    "variant_family": "B4",
    "runs": "2",
    "mean_p_event": "0.9451018604040146",
    "delta_p_event": "0.34760692214965816",
    "ci95_delta_p_event": "0.024426938514709493",
    "up_rate_p_event": "",
    "mean_illegal_mass": "0.05489813959598544",
    "delta_illegal_mass": "-0.34760692214965816",
    "low_p_event_rate": "0.0",
    "unconstrained_event_rate": "1.0",
    "delta_unconstrained_event_rate": "0.030000000000000027",
    "up_rate_legal": "",
    "constrained_event_rate": "1.0",
    "char_accuracy": "0.532",
    "delta_char_accuracy": "-0.0023333333333332984",
    "up_rate_char": "",
    "constrained_char_accuracy": "0.532",
    "delta_constrained_char_accuracy": "-0.0043333333333333",
    "exact_sequence_accuracy": "0.002",
    "delta_exact_sequence_accuracy": "0.0",
    "up_rate_exact": "",
    "constrained_exact_sequence_accuracy": "0.002",
    "delta_constrained_exact_sequence_accuracy": "0.0",
    "mean_nll": "2.193607892513275",
    "hidden_conflict_rate": "0.0",
    "fairness_flags": "warn_b1_b3_not_independent_rows;warn_partial_baseline_grid",
    "claim_use": "partial semi-real evidence",
    "notes": ""
  },
  {
    "block": "learning_curve",
    "task_family": "semi_real_field",
    "task": "product_code",
    "setting": "labeled25_unlabeled100",
    "variant": "B0_unconstrained",
    "variant_family": "B0",
    "runs": "2",
    "mean_p_event": "0.7659271821081639",
    "delta_p_event": "0.0",
    "ci95_delta_p_event": "0.0",
    "up_rate_p_event": "",
    "mean_illegal_mass": "0.23407281789183615",
    "delta_illegal_mass": "0.0",
    "low_p_event_rate": "0.038",
    "unconstrained_event_rate": "0.956",
    "delta_unconstrained_event_rate": "0.0",
    "up_rate_legal": "",
    "constrained_event_rate": "1.0",
    "char_accuracy": "0.7206666666666667",
    "delta_char_accuracy": "0.0",
    "up_rate_char": "",
    "constrained_char_accuracy": "0.7256666666666667",
    "delta_constrained_char_accuracy": "0.0",
    "exact_sequence_accuracy": "0.062",
    "delta_exact_sequence_accuracy": "0.0",
    "up_rate_exact": "",
    "constrained_exact_sequence_accuracy": "0.062",
    "delta_constrained_exact_sequence_accuracy": "0.0",
    "mean_nll": "0.9591370991071065",
    "hidden_conflict_rate": "0.038",
    "fairness_flags": "warn_b1_b3_not_independent_rows;warn_partial_baseline_grid",
    "claim_use": "partial semi-real evidence",
    "notes": ""
  },
  {
    "block": "learning_curve",
    "task_family": "semi_real_field",
    "task": "product_code",
    "setting": "labeled25_unlabeled100",
    "variant": "B4_semi_event_0.1",
    "variant_family": "B4",
    "runs": "2",
    "mean_p_event": "0.9344412693977355",
    "delta_p_event": "0.16851408728957173",
    "ci95_delta_p_event": "0.015754257715940505",
    "up_rate_p_event": "",
    "mean_illegal_mass": "0.06555873060226441",
    "delta_illegal_mass": "-0.16851408728957173",
    "low_p_event_rate": "0.0",
    "unconstrained_event_rate": "1.0",
    "delta_unconstrained_event_rate": "0.04400000000000004",
    "up_rate_legal": "",
    "constrained_event_rate": "1.0",
    "char_accuracy": "0.7503333333333333",
    "delta_char_accuracy": "0.029666666666666675",
    "up_rate_char": "",
    "constrained_char_accuracy": "0.7503333333333333",
    "delta_constrained_char_accuracy": "0.02466666666666667",
    "exact_sequence_accuracy": "0.11399999999999999",
    "delta_exact_sequence_accuracy": "0.052",
    "up_rate_exact": "",
    "constrained_exact_sequence_accuracy": "0.11399999999999999",
    "delta_constrained_exact_sequence_accuracy": "0.052",
    "mean_nll": "0.9467596293290457",
    "hidden_conflict_rate": "0.0",
    "fairness_flags": "warn_b1_b3_not_independent_rows;warn_partial_baseline_grid",
    "claim_use": "partial semi-real evidence",
    "notes": ""
  },
  {
    "block": "learning_curve",
    "task_family": "semi_real_field",
    "task": "product_code",
    "setting": "labeled50_unlabeled100",
    "variant": "B0_unconstrained",
    "variant_family": "B0",
    "runs": "2",
    "mean_p_event": "0.8577327162623405",
    "delta_p_event": "0.0",
    "ci95_delta_p_event": "0.0",
    "up_rate_p_event": "",
    "mean_illegal_mass": "0.14226728373765946",
    "delta_illegal_mass": "0.0",
    "low_p_event_rate": "0.008",
    "unconstrained_event_rate": "0.974",
    "delta_unconstrained_event_rate": "0.0",
    "up_rate_legal": "",
    "constrained_event_rate": "1.0",
    "char_accuracy": "0.8956666666666666",
    "delta_char_accuracy": "0.0",
    "up_rate_char": "",
    "constrained_char_accuracy": "0.9016666666666666",
    "delta_constrained_char_accuracy": "0.0",
    "exact_sequence_accuracy": "0.494",
    "delta_exact_sequence_accuracy": "0.0",
    "up_rate_exact": "",
    "constrained_exact_sequence_accuracy": "0.502",
    "delta_constrained_exact_sequence_accuracy": "0.0",
    "mean_nll": "0.4151674122810364",
    "hidden_conflict_rate": "0.008",
    "fairness_flags": "warn_b1_b3_not_independent_rows;warn_partial_baseline_grid",
    "claim_use": "partial semi-real evidence",
    "notes": ""
  },
  {
    "block": "learning_curve",
    "task_family": "semi_real_field",
    "task": "product_code",
    "setting": "labeled50_unlabeled100",
    "variant": "B4_semi_event_0.1",
    "variant_family": "B4",
    "runs": "2",
    "mean_p_event": "0.9515719822645188",
    "delta_p_event": "0.09383926600217818",
    "ci95_delta_p_event": "0.015933158481121045",
    "up_rate_p_event": "",
    "mean_illegal_mass": "0.04842801773548128",
    "delta_illegal_mass": "-0.09383926600217818",
    "low_p_event_rate": "0.0",
    "unconstrained_event_rate": "1.0",
    "delta_unconstrained_event_rate": "0.026000000000000023",
    "up_rate_legal": "",
    "constrained_event_rate": "1.0",
    "char_accuracy": "0.9226666666666667",
    "delta_char_accuracy": "0.027000000000000024",
    "up_rate_char": "",
    "constrained_char_accuracy": "0.9226666666666667",
    "delta_constrained_char_accuracy": "0.02100000000000002",
    "exact_sequence_accuracy": "0.5900000000000001",
    "delta_exact_sequence_accuracy": "0.096",
    "up_rate_exact": "",
    "constrained_exact_sequence_accuracy": "0.5900000000000001",
    "delta_constrained_exact_sequence_accuracy": "0.088",
    "mean_nll": "0.3221209081808726",
    "hidden_conflict_rate": "0.0",
    "fairness_flags": "warn_b1_b3_not_independent_rows;warn_partial_baseline_grid",
    "claim_use": "partial semi-real evidence",
    "notes": ""
  },
  {
    "block": "learning_curve",
    "task_family": "semi_real_field",
    "task": "product_code",
    "setting": "labeled5_unlabeled100",
    "variant": "B0_unconstrained",
    "variant_family": "B0",
    "runs": "2",
    "mean_p_event": "0.2319360100366175",
    "delta_p_event": "0.0",
    "ci95_delta_p_event": "0.0",
    "up_rate_p_event": "",
    "mean_illegal_mass": "0.7680639899633825",
    "delta_illegal_mass": "0.0",
    "low_p_event_rate": "0.996",
    "unconstrained_event_rate": "0.8919999999999999",
    "delta_unconstrained_event_rate": "0.0",
    "up_rate_legal": "",
    "constrained_event_rate": "1.0",
    "char_accuracy": "0.4126666666666667",
    "delta_char_accuracy": "0.0",
    "up_rate_char": "",
    "constrained_char_accuracy": "0.41933333333333334",
    "delta_constrained_char_accuracy": "0.0",
    "exact_sequence_accuracy": "0.002",
    "delta_exact_sequence_accuracy": "0.0",
    "up_rate_exact": "",
    "constrained_exact_sequence_accuracy": "0.002",
    "delta_constrained_exact_sequence_accuracy": "0.0",
    "mean_nll": "2.4156664783159894",
    "hidden_conflict_rate": "0.996",
    "fairness_flags": "warn_b1_b3_not_independent_rows;warn_partial_baseline_grid",
    "claim_use": "partial semi-real evidence",
    "notes": ""
  },
  {
    "block": "learning_curve",
    "task_family": "semi_real_field",
    "task": "product_code",
    "setting": "labeled5_unlabeled100",
    "variant": "B4_semi_event_0.1",
    "variant_family": "B4",
    "runs": "2",
    "mean_p_event": "0.9636446316242218",
    "delta_p_event": "0.7317086215876043",
    "ci95_delta_p_event": "0.056169498665183774",
    "up_rate_p_event": "",
    "mean_illegal_mass": "0.036355368375778185",
    "delta_illegal_mass": "-0.7317086215876043",
    "low_p_event_rate": "0.0",
    "unconstrained_event_rate": "1.0",
    "delta_unconstrained_event_rate": "0.10800000000000004",
    "up_rate_legal": "",
    "constrained_event_rate": "1.0",
    "char_accuracy": "0.434",
    "delta_char_accuracy": "0.021333333333333315",
    "up_rate_char": "",
    "constrained_char_accuracy": "0.434",
    "delta_constrained_char_accuracy": "0.014666666666666661",
    "exact_sequence_accuracy": "0.002",
    "delta_exact_sequence_accuracy": "0.0",
    "up_rate_exact": "",
    "constrained_exact_sequence_accuracy": "0.002",
    "delta_constrained_exact_sequence_accuracy": "0.0",
    "mean_nll": "2.8426462926864624",
    "hidden_conflict_rate": "0.0",
    "fairness_flags": "warn_b1_b3_not_independent_rows;warn_partial_baseline_grid",
    "claim_use": "partial semi-real evidence",
    "notes": ""
  },
  {
    "block": "lambda_tradeoff",
    "task_family": "semi_real_field",
    "task": "amount",
    "setting": "labeled25_unlabeled100",
    "variant": "B0_unconstrained",
    "variant_family": "B0",
    "runs": "2",
    "mean_p_event": "0.7834720315933228",
    "delta_p_event": "0.0",
    "ci95_delta_p_event": "0.0",
    "up_rate_p_event": "",
    "mean_illegal_mass": "0.21652796840667726",
    "delta_illegal_mass": "0.0",
    "low_p_event_rate": "0.016",
    "unconstrained_event_rate": "0.918",
    "delta_unconstrained_event_rate": "0.0",
    "up_rate_legal": "",
    "constrained_event_rate": "1.0",
    "char_accuracy": "0.8076666666666668",
    "delta_char_accuracy": "0.0",
    "up_rate_char": "",
    "constrained_char_accuracy": "0.8083333333333333",
    "delta_constrained_char_accuracy": "0.0",
    "exact_sequence_accuracy": "0.192",
    "delta_exact_sequence_accuracy": "0.0",
    "up_rate_exact": "",
    "constrained_exact_sequence_accuracy": "0.192",
    "delta_constrained_exact_sequence_accuracy": "0.0",
    "mean_nll": "0.6287848156293234",
    "hidden_conflict_rate": "0.016",
    "fairness_flags": "warn_b1_b3_not_independent_rows;warn_partial_baseline_grid",
    "claim_use": "partial semi-real evidence",
    "notes": ""
  },
  {
    "block": "lambda_tradeoff",
    "task_family": "semi_real_field",
    "task": "amount",
    "setting": "labeled25_unlabeled100",
    "variant": "B4_semi_event_0.05",
    "variant_family": "B4",
    "runs": "2",
    "mean_p_event": "0.9065845540761948",
    "delta_p_event": "0.12311252248287202",
    "ci95_delta_p_event": "0.0219875899267197",
    "up_rate_p_event": "",
    "mean_illegal_mass": "0.09341544592380524",
    "delta_illegal_mass": "-0.12311252248287202",
    "low_p_event_rate": "0.0",
    "unconstrained_event_rate": "1.0",
    "delta_unconstrained_event_rate": "0.08199999999999996",
    "up_rate_legal": "",
    "constrained_event_rate": "1.0",
    "char_accuracy": "0.8343333333333334",
    "delta_char_accuracy": "0.026666666666666616",
    "up_rate_char": "",
    "constrained_char_accuracy": "0.8343333333333334",
    "delta_constrained_char_accuracy": "0.025999999999999968",
    "exact_sequence_accuracy": "0.264",
    "delta_exact_sequence_accuracy": "0.07200000000000002",
    "up_rate_exact": "",
    "constrained_exact_sequence_accuracy": "0.264",
    "delta_constrained_exact_sequence_accuracy": "0.07200000000000002",
    "mean_nll": "0.5622509489059448",
    "hidden_conflict_rate": "0.0",
    "fairness_flags": "warn_b1_b3_not_independent_rows;warn_partial_baseline_grid",
    "claim_use": "partial semi-real evidence",
    "notes": ""
  },
  {
    "block": "lambda_tradeoff",
    "task_family": "semi_real_field",
    "task": "amount",
    "setting": "labeled25_unlabeled100",
    "variant": "B4_semi_event_0.1",
    "variant_family": "B4",
    "runs": "2",
    "mean_p_event": "0.9297657436132432",
    "delta_p_event": "0.14629371201992036",
    "ci95_delta_p_event": "0.026588551774024936",
    "up_rate_p_event": "",
    "mean_illegal_mass": "0.0702342563867569",
    "delta_illegal_mass": "-0.14629371201992036",
    "low_p_event_rate": "0.0",
    "unconstrained_event_rate": "1.0",
    "delta_unconstrained_event_rate": "0.08199999999999996",
    "up_rate_legal": "",
    "constrained_event_rate": "1.0",
    "char_accuracy": "0.8313333333333333",
    "delta_char_accuracy": "0.023666666666666614",
    "up_rate_char": "",
    "constrained_char_accuracy": "0.8313333333333333",
    "delta_constrained_char_accuracy": "0.022999999999999965",
    "exact_sequence_accuracy": "0.252",
    "delta_exact_sequence_accuracy": "0.06000000000000001",
    "up_rate_exact": "",
    "constrained_exact_sequence_accuracy": "0.252",
    "delta_constrained_exact_sequence_accuracy": "0.06000000000000001",
    "mean_nll": "0.5740329697926839",
    "hidden_conflict_rate": "0.0",
    "fairness_flags": "warn_b1_b3_not_independent_rows;warn_partial_baseline_grid",
    "claim_use": "partial semi-real evidence",
    "notes": ""
  },
  {
    "block": "lambda_tradeoff",
    "task_family": "semi_real_field",
    "task": "amount",
    "setting": "labeled25_unlabeled100",
    "variant": "B4_semi_event_0.2",
    "variant_family": "B4",
    "runs": "2",
    "mean_p_event": "0.9476383384466172",
    "delta_p_event": "0.16416630685329442",
    "ci95_delta_p_event": "0.027290429987907427",
    "up_rate_p_event": "",
    "mean_illegal_mass": "0.05236166155338284",
    "delta_illegal_mass": "-0.16416630685329442",
    "low_p_event_rate": "0.0",
    "unconstrained_event_rate": "1.0",
    "delta_unconstrained_event_rate": "0.08199999999999996",
    "up_rate_legal": "",
    "constrained_event_rate": "1.0",
    "char_accuracy": "0.825",
    "delta_char_accuracy": "0.01733333333333331",
    "up_rate_char": "",
    "constrained_char_accuracy": "0.825",
    "delta_constrained_char_accuracy": "0.016666666666666663",
    "exact_sequence_accuracy": "0.246",
    "delta_exact_sequence_accuracy": "0.054000000000000006",
    "up_rate_exact": "",
    "constrained_exact_sequence_accuracy": "0.246",
    "delta_constrained_exact_sequence_accuracy": "0.054000000000000006",
    "mean_nll": "0.584112902323405",
    "hidden_conflict_rate": "0.0",
    "fairness_flags": "warn_b1_b3_not_independent_rows;warn_partial_baseline_grid",
    "claim_use": "partial semi-real evidence",
    "notes": ""
  },
  {
    "block": "lambda_tradeoff",
    "task_family": "semi_real_field",
    "task": "amount",
    "setting": "labeled25_unlabeled100",
    "variant": "B4_semi_event_0.5",
    "variant_family": "B4",
    "runs": "2",
    "mean_p_event": "0.965770237326622",
    "delta_p_event": "0.1822982057332993",
    "ci95_delta_p_event": "0.028343686337470978",
    "up_rate_p_event": "",
    "mean_illegal_mass": "0.03422976267337796",
    "delta_illegal_mass": "-0.1822982057332993",
    "low_p_event_rate": "0.0",
    "unconstrained_event_rate": "1.0",
    "delta_unconstrained_event_rate": "0.08199999999999996",
    "up_rate_legal": "",
    "constrained_event_rate": "1.0",
    "char_accuracy": "0.8216666666666667",
    "delta_char_accuracy": "0.013999999999999957",
    "up_rate_char": "",
    "constrained_char_accuracy": "0.8216666666666667",
    "delta_constrained_char_accuracy": "0.013333333333333308",
    "exact_sequence_accuracy": "0.258",
    "delta_exact_sequence_accuracy": "0.06600000000000002",
    "up_rate_exact": "",
    "constrained_exact_sequence_accuracy": "0.258",
    "delta_constrained_exact_sequence_accuracy": "0.06600000000000002",
    "mean_nll": "0.6264448091189067",
    "hidden_conflict_rate": "0.0",
    "fairness_flags": "warn_b1_b3_not_independent_rows;warn_partial_baseline_grid",
    "claim_use": "partial semi-real evidence",
    "notes": ""
  },
  {
    "block": "lambda_tradeoff",
    "task_family": "semi_real_field",
    "task": "amount",
    "setting": "labeled25_unlabeled100",
    "variant": "B4_semi_event_1.0",
    "variant_family": "B4",
    "runs": "2",
    "mean_p_event": "0.9772406868934631",
    "delta_p_event": "0.19376865530014042",
    "ci95_delta_p_event": "0.027858658647537247",
    "up_rate_p_event": "",
    "mean_illegal_mass": "0.022759313106536838",
    "delta_illegal_mass": "-0.19376865530014042",
    "low_p_event_rate": "0.0",
    "unconstrained_event_rate": "1.0",
    "delta_unconstrained_event_rate": "0.08199999999999996",
    "up_rate_legal": "",
    "constrained_event_rate": "1.0",
    "char_accuracy": "0.8143333333333334",
    "delta_char_accuracy": "0.006666666666666654",
    "up_rate_char": "",
    "constrained_char_accuracy": "0.8143333333333334",
    "delta_constrained_char_accuracy": "0.006000000000000005",
    "exact_sequence_accuracy": "0.23",
    "delta_exact_sequence_accuracy": "0.03800000000000002",
    "up_rate_exact": "",
    "constrained_exact_sequence_accuracy": "0.23",
    "delta_constrained_exact_sequence_accuracy": "0.03800000000000002",
    "mean_nll": "0.6287277050018311",
    "hidden_conflict_rate": "0.0",
    "fairness_flags": "warn_b1_b3_not_independent_rows;warn_partial_baseline_grid",
    "claim_use": "partial semi-real evidence",
    "notes": ""
  },
  {
    "block": "lambda_tradeoff",
    "task_family": "semi_real_field",
    "task": "product_code",
    "setting": "labeled25_unlabeled100",
    "variant": "B0_unconstrained",
    "variant_family": "B0",
    "runs": "2",
    "mean_p_event": "0.7659271821081639",
    "delta_p_event": "0.0",
    "ci95_delta_p_event": "0.0",
    "up_rate_p_event": "",
    "mean_illegal_mass": "0.23407281789183615",
    "delta_illegal_mass": "0.0",
    "low_p_event_rate": "0.038",
    "unconstrained_event_rate": "0.956",
    "delta_unconstrained_event_rate": "0.0",
    "up_rate_legal": "",
    "constrained_event_rate": "1.0",
    "char_accuracy": "0.7206666666666667",
    "delta_char_accuracy": "0.0",
    "up_rate_char": "",
    "constrained_char_accuracy": "0.7256666666666667",
    "delta_constrained_char_accuracy": "0.0",
    "exact_sequence_accuracy": "0.062",
    "delta_exact_sequence_accuracy": "0.0",
    "up_rate_exact": "",
    "constrained_exact_sequence_accuracy": "0.062",
    "delta_constrained_exact_sequence_accuracy": "0.0",
    "mean_nll": "0.9591370991071065",
    "hidden_conflict_rate": "0.038",
    "fairness_flags": "warn_b1_b3_not_independent_rows;warn_partial_baseline_grid",
    "claim_use": "partial semi-real evidence",
    "notes": ""
  },
  {
    "block": "lambda_tradeoff",
    "task_family": "semi_real_field",
    "task": "product_code",
    "setting": "labeled25_unlabeled100",
    "variant": "B4_semi_event_0.05",
    "variant_family": "B4",
    "runs": "2",
    "mean_p_event": "0.9051084253787994",
    "delta_p_event": "0.13918124327063558",
    "ci95_delta_p_event": "0.011546541785001738",
    "up_rate_p_event": "",
    "mean_illegal_mass": "0.09489157462120057",
    "delta_illegal_mass": "-0.13918124327063558",
    "low_p_event_rate": "0.0",
    "unconstrained_event_rate": "0.996",
    "delta_unconstrained_event_rate": "0.040000000000000036",
    "up_rate_legal": "",
    "constrained_event_rate": "1.0",
    "char_accuracy": "0.7546666666666666",
    "delta_char_accuracy": "0.033999999999999975",
    "up_rate_char": "",
    "constrained_char_accuracy": "0.755",
    "delta_constrained_char_accuracy": "0.029333333333333322",
    "exact_sequence_accuracy": "0.118",
    "delta_exact_sequence_accuracy": "0.056",
    "up_rate_exact": "",
    "constrained_exact_sequence_accuracy": "0.118",
    "delta_constrained_exact_sequence_accuracy": "0.056",
    "mean_nll": "0.9295359709262847",
    "hidden_conflict_rate": "0.0",
    "fairness_flags": "warn_b1_b3_not_independent_rows;warn_partial_baseline_grid",
    "claim_use": "partial semi-real evidence",
    "notes": ""
  },
  {
    "block": "lambda_tradeoff",
    "task_family": "semi_real_field",
    "task": "product_code",
    "setting": "labeled25_unlabeled100",
    "variant": "B4_semi_event_0.1",
    "variant_family": "B4",
    "runs": "2",
    "mean_p_event": "0.9344412693977355",
    "delta_p_event": "0.16851408728957173",
    "ci95_delta_p_event": "0.015754257715940505",
    "up_rate_p_event": "",
    "mean_illegal_mass": "0.06555873060226441",
    "delta_illegal_mass": "-0.16851408728957173",
    "low_p_event_rate": "0.0",
    "unconstrained_event_rate": "1.0",
    "delta_unconstrained_event_rate": "0.04400000000000004",
    "up_rate_legal": "",
    "constrained_event_rate": "1.0",
    "char_accuracy": "0.7503333333333333",
    "delta_char_accuracy": "0.029666666666666675",
    "up_rate_char": "",
    "constrained_char_accuracy": "0.7503333333333333",
    "delta_constrained_char_accuracy": "0.02466666666666667",
    "exact_sequence_accuracy": "0.11399999999999999",
    "delta_exact_sequence_accuracy": "0.052",
    "up_rate_exact": "",
    "constrained_exact_sequence_accuracy": "0.11399999999999999",
    "delta_constrained_exact_sequence_accuracy": "0.052",
    "mean_nll": "0.9467596293290457",
    "hidden_conflict_rate": "0.0",
    "fairness_flags": "warn_b1_b3_not_independent_rows;warn_partial_baseline_grid",
    "claim_use": "partial semi-real evidence",
    "notes": ""
  },
  {
    "block": "lambda_tradeoff",
    "task_family": "semi_real_field",
    "task": "product_code",
    "setting": "labeled25_unlabeled100",
    "variant": "B4_semi_event_0.2",
    "variant_family": "B4",
    "runs": "2",
    "mean_p_event": "0.9562378143072128",
    "delta_p_event": "0.19031063219904898",
    "ci95_delta_p_event": "0.018808318971395652",
    "up_rate_p_event": "",
    "mean_illegal_mass": "0.04376218569278717",
    "delta_illegal_mass": "-0.19031063219904898",
    "low_p_event_rate": "0.0",
    "unconstrained_event_rate": "1.0",
    "delta_unconstrained_event_rate": "0.04400000000000004",
    "up_rate_legal": "",
    "constrained_event_rate": "1.0",
    "char_accuracy": "0.746",
    "delta_char_accuracy": "0.02533333333333332",
    "up_rate_char": "",
    "constrained_char_accuracy": "0.746",
    "delta_constrained_char_accuracy": "0.020333333333333314",
    "exact_sequence_accuracy": "0.108",
    "delta_exact_sequence_accuracy": "0.046",
    "up_rate_exact": "",
    "constrained_exact_sequence_accuracy": "0.108",
    "delta_constrained_exact_sequence_accuracy": "0.046",
    "mean_nll": "0.9690959590276083",
    "hidden_conflict_rate": "0.0",
    "fairness_flags": "warn_b1_b3_not_independent_rows;warn_partial_baseline_grid",
    "claim_use": "partial semi-real evidence",
    "notes": ""
  },
  {
    "block": "lambda_tradeoff",
    "task_family": "semi_real_field",
    "task": "product_code",
    "setting": "labeled25_unlabeled100",
    "variant": "B4_semi_event_0.5",
    "variant_family": "B4",
    "runs": "2",
    "mean_p_event": "0.9740294833183288",
    "delta_p_event": "0.20810230121016499",
    "ci95_delta_p_event": "0.020153563078642005",
    "up_rate_p_event": "",
    "mean_illegal_mass": "0.025970516681671163",
    "delta_illegal_mass": "-0.20810230121016499",
    "low_p_event_rate": "0.0",
    "unconstrained_event_rate": "1.0",
    "delta_unconstrained_event_rate": "0.04400000000000004",
    "up_rate_legal": "",
    "constrained_event_rate": "1.0",
    "char_accuracy": "0.743",
    "delta_char_accuracy": "0.022333333333333316",
    "up_rate_char": "",
    "constrained_char_accuracy": "0.743",
    "delta_constrained_char_accuracy": "0.01733333333333331",
    "exact_sequence_accuracy": "0.098",
    "delta_exact_sequence_accuracy": "0.036000000000000004",
    "up_rate_exact": "",
    "constrained_exact_sequence_accuracy": "0.098",
    "delta_constrained_exact_sequence_accuracy": "0.036000000000000004",
    "mean_nll": "1.0003005897204083",
    "hidden_conflict_rate": "0.0",
    "fairness_flags": "warn_b1_b3_not_independent_rows;warn_partial_baseline_grid",
    "claim_use": "partial semi-real evidence",
    "notes": ""
  },
  {
    "block": "lambda_tradeoff",
    "task_family": "semi_real_field",
    "task": "product_code",
    "setting": "labeled25_unlabeled100",
    "variant": "B4_semi_event_1.0",
    "variant_family": "B4",
    "runs": "2",
    "mean_p_event": "0.9838805527687073",
    "delta_p_event": "0.21795337066054343",
    "ci95_delta_p_event": "0.023013968733549137",
    "up_rate_p_event": "",
    "mean_illegal_mass": "0.016119447231292716",
    "delta_illegal_mass": "-0.21795337066054343",
    "low_p_event_rate": "0.0",
    "unconstrained_event_rate": "1.0",
    "delta_unconstrained_event_rate": "0.04400000000000004",
    "up_rate_legal": "",
    "constrained_event_rate": "1.0",
    "char_accuracy": "0.73",
    "delta_char_accuracy": "0.009333333333333305",
    "up_rate_char": "",
    "constrained_char_accuracy": "0.73",
    "delta_constrained_char_accuracy": "0.0043333333333333",
    "exact_sequence_accuracy": "0.082",
    "delta_exact_sequence_accuracy": "0.020000000000000004",
    "up_rate_exact": "",
    "constrained_exact_sequence_accuracy": "0.082",
    "delta_constrained_exact_sequence_accuracy": "0.020000000000000004",
    "mean_nll": "1.0318803731600443",
    "hidden_conflict_rate": "0.0",
    "fairness_flags": "warn_b1_b3_not_independent_rows;warn_partial_baseline_grid",
    "claim_use": "partial semi-real evidence",
    "notes": ""
  }
]